vnpy_sec/__init__.py
vnpy_sec/api/DFITCSECMdApi.dll
vnpy_sec/api/DFITCSECTraderApi.dll
vnpy_sec/api/HsFutuSystemInfo.dll
vnpy_sec/api/InformationCollect.dll
vnpy_sec/api/__init__.py
vnpy_sec/api/sec_constant.py
vnpy_sec/api/vnsecmd.pyd
vnpy_sec/api/vnsectd.pyd
vnpy_sec/api/generator/DFITC_md_header_define.h
vnpy_sec/api/generator/DFITC_md_header_function.h
vnpy_sec/api/generator/DFITC_md_header_on.h
vnpy_sec/api/generator/DFITC_md_header_process.h
vnpy_sec/api/generator/DFITC_md_source_function.cpp
vnpy_sec/api/generator/DFITC_md_source_module.cpp
vnpy_sec/api/generator/DFITC_md_source_on.cpp
vnpy_sec/api/generator/DFITC_md_source_process.cpp
vnpy_sec/api/generator/DFITC_md_source_switch.cpp
vnpy_sec/api/generator/DFITC_md_source_task.cpp
vnpy_sec/api/generator/DFITC_td_header_define.h
vnpy_sec/api/generator/DFITC_td_header_function.h
vnpy_sec/api/generator/DFITC_td_header_on.h
vnpy_sec/api/generator/DFITC_td_header_process.h
vnpy_sec/api/generator/DFITC_td_source_function.cpp
vnpy_sec/api/generator/DFITC_td_source_module.cpp
vnpy_sec/api/generator/DFITC_td_source_on.cpp
vnpy_sec/api/generator/DFITC_td_source_process.cpp
vnpy_sec/api/generator/DFITC_td_source_switch.cpp
vnpy_sec/api/generator/DFITC_td_source_task.cpp
vnpy_sec/api/include/DFITCSECApiDataType.h
vnpy_sec/api/include/DFITCSECApiStruct.h
vnpy_sec/api/include/DFITCSECMdApi.h
vnpy_sec/api/include/DFITCSECTraderApi.h
vnpy_sec/api/include/pybind11/attr.h
vnpy_sec/api/include/pybind11/buffer_info.h
vnpy_sec/api/include/pybind11/cast.h
vnpy_sec/api/include/pybind11/chrono.h
vnpy_sec/api/include/pybind11/common.h
vnpy_sec/api/include/pybind11/complex.h
vnpy_sec/api/include/pybind11/eigen.h
vnpy_sec/api/include/pybind11/embed.h
vnpy_sec/api/include/pybind11/eval.h
vnpy_sec/api/include/pybind11/functional.h
vnpy_sec/api/include/pybind11/iostream.h
vnpy_sec/api/include/pybind11/numpy.h
vnpy_sec/api/include/pybind11/operators.h
vnpy_sec/api/include/pybind11/options.h
vnpy_sec/api/include/pybind11/pybind11.h
vnpy_sec-1.0.3.dist-info/LICENSE
vnpy_sec-1.0.3.dist-info/METADATA
vnpy_sec-1.0.3.dist-info/WHEEL
vnpy_sec-1.0.3.dist-info/top_level.txt
vnpy_sec-1.0.3.dist-info/RECORD
